nonebot_plugin_binance/__init__.py
nonebot_plugin_binance/api.py
nonebot_plugin_binance/auth.py
nonebot_plugin_binance/config.py
nonebot_plugin_binance/drawer.py
nonebot_plugin_binance/websocket.py
nonebot_plugin_binance/handlers/alert.py
nonebot_plugin_binance/handlers/market.py
nonebot_plugin_binance/handlers/system.py
nonebot_plugin_binance/handlers/trade.py
nonebot_plugin_binance/templates/account_snapshot.html
nonebot_plugin_binance/templates/alert_list.html
nonebot_plugin_binance/templates/base.html
nonebot_plugin_binance/templates/help.html
nonebot_plugin_binance/templates/multi_kline.html
nonebot_plugin_binance/templates/multi_ticker.html
nonebot_plugin_binance/templates/orders.html
nonebot_plugin_binance/templates/positions.html
nonebot_plugin_binance/templates/status.html
nonebot_plugin_binance/templates/style.css
nonebot_plugin_binance-0.0.9.dist-info/licenses/LICENSE
nonebot_plugin_binance-0.0.9.dist-info/METADATA
nonebot_plugin_binance-0.0.9.dist-info/WHEEL
nonebot_plugin_binance-0.0.9.dist-info/top_level.txt
nonebot_plugin_binance-0.0.9.dist-info/RECORD
