Metadata-Version: 2.4
Name: nonebot-plugin-binance
Version: 0.0.9
Summary: 一个币安(Binance)插件，提供行情、交易、资产查询和实时价格预警功能。
Author-email: newcovid <280310454@qq.com>
Project-URL: Homepage, https://github.com/newcovid/nonebot-plugin-binance
Project-URL: Documentation, https://github.com/newcovid/nonebot-plugin-binance#readme
Keywords: nonebot,nonebot2,binance,crypto,trade,finance
Requires-Python: >=3.9
License-File: LICENSE
Requires-Dist: nonebot2>=2.3.0
Requires-Dist: nonebot-adapter-onebot>=2.3.0
Requires-Dist: nonebot-plugin-htmlrender>=0.3.0
Requires-Dist: nonebot-plugin-localstore>=0.7.0
Requires-Dist: aiohttp>=3.8.0
Requires-Dist: cryptography>=41.0.0
Requires-Dist: websockets>=11.0.0
Requires-Dist: pydantic>=1.10.0
Dynamic: license-file
